# 虚拟机执行子系统



## 1. 类文件结构



### 1.1 概述

**Java 虚拟机不和包括 java 在内的任何语言绑定，它只与“Class文件”有所关联**

任何语言只要能编译成 Class 文件都能在虚拟机上运行，如：Clojure、Groovy、JRuby、Jython、Scala



### 1.2 Class 类文件的结构

[oracle javaFile structure](https://docs.oracle.com/javase/specs/jvms/se15/html/jvms-4.html)

| 名称                | 中文名称     | 字节数（个）   | 数量                  |
| ------------------- | ------------ | -------------- | --------------------- |
| magic               | 魔数         | 4              | 1                     |
| Minor Version       | 次版本号     | 2              | 1                     |
| Major Version       | 主版本号     | 2              | 1                     |
| constant_pool_count | 常量池计数器 | 2              | 1                     |
| constant_pool       | 常量池       | cp_info        | constant_pool_count-1 |
| access_flags        | 访问标志     | 2              | 1                     |
| this_class          | 当前类名     | 2              | 1                     |
| super_class         | 父类名称     | 2              | 1                     |
| interfaces_count    | 接口数量     | 2              | 1                     |
| interfaces          | 接口信息     | 2              | interfaces_count      |
| fields_count        | 字段数量     | 2              | 1                     |
| fields              | 字段         | field_info     | fields_count          |
| methods_count       | 方法数量     | 2              | 1                     |
| method              | 方法         | method_info    | methods_count         |
| attributes_count    | 附加属性数量 | 2              | 1                     |
| attributes          | 附加属性     | attribute_info | attributes_count      |

- **magic**: 魔数的固定值为：0xCAFEBABE，JVM可以根据文件的开头来判断这个文件是否可能是一个.class文件，如果是，才会继续进行之后的操作

- **Minor Version:**  次版本号

- **Major Version:** 主要版本号

  | Java SE | Released       | Major | Supported majors |
  | ------- | -------------- | ----- | ---------------- |
  | 1.0.2   | May 1996       | 45    | 45               |
  | 1.1     | February 1997  | 45    | 45               |
  | 1.2     | December 1998  | 46    | 45 .. 46         |
  | 1.3     | May 2000       | 47    | 45 .. 47         |
  | 1.4     | February 2002  | 48    | 45 .. 48         |
  | 5.0     | September 2004 | 49    | 45 .. 49         |
  | 6       | December 2006  | 50    | 45 .. 50         |
  | 7       | July 2011      | 51    | 45 .. 51         |
  | 8       | March 2014     | 52    | 45 .. 52         |
  | 9       | September 2017 | 53    | 45 .. 53         |
  | 10      | March 2018     | 54    | 45 .. 54         |
  | 11      | September 2018 | 55    | 45 .. 55         |
  | 12      | March 2019     | 56    | 45 .. 56         |
  | 13      | September 2019 | 57    | 45 .. 57         |
  | 14      | March 2020     | 58    | 45 .. 58         |
  | 15      | September 2020 | 59    | 45 .. 59         |

- **constant_pool：** constant_pool_count 记录了常量池里面常量的数量，常量的长度是不固定的。参考：[官方文档](https://docs.oracle.com/javase/specs/jvms/se15/html/jvms-4.html#jvms-4.4)

- **access_flags：** 访问标志，常量池结束之后的两个字节，描述该Class是类还是接口，以及是否被Public、Abstract、Final等修饰符修饰。

  | Flag Name        | Value  | Interpretation           |
  | ---------------- | ------ | ------------------------ |
  | `ACC_PUBLIC`     | 0x0001 | 字段为 `public`          |
  | `ACC_FINAL`      | 0x0010 | 字段为 `final`           |
  | `ACC_SUPER`      | 0x0020 | 调用父类方法             |
  | `ACC_INTERFACE`  | 0x0200 | 是一个接口               |
  | `ACC_ABSTRACT`   | 0x0400 | `abstract`;抽象类        |
  | `ACC_SYNTHETIC`  | 0x1000 | 字段是否由编译器自动产生 |
  | `ACC_ANNOTATION` | 0x2000 | 为一个注解               |
  | `ACC_ENUM`       | 0x4000 | 字段为 `enum` 类型.      |
  | `ACC_MODULE`     | 0x8000 | 为一个 `method`          |

  





#### 附录：完整代码和class文件

**ResultBean.class**

```java
package com.yui.tool.dynamic.dubbo.dto;

import java.io.Serializable;

/**
 * @author XuZhuohao
 * @date 2019/10/18
 */
public class ResultBean<T>  implements Serializable {
    private boolean isSuccess;
    private int responseCode;
    private String responseMsg;
    private T data;

    public ResultBean() {
    }

    public ResultBean<T> toSuccess(T data){
        this.setData(data);
        this.setResponseCode(0);
        this.setResponseMsg("操作成功！");
        this.setIsSuccess(true);
        return this;
    }
    public ResultBean<T> toFail(String responseMsg){
        return this.setResponseCode(-1).setResponseMsg(responseMsg).setIsSuccess(false);
    }

    public boolean getIsSuccess() {
        return isSuccess;
    }

    public ResultBean<T> setIsSuccess(boolean success) {
        isSuccess = success;
        return this;
    }

    public int getResponseCode() {
        return responseCode;
    }

    public ResultBean<T> setResponseCode(int responseCode) {
        this.responseCode = responseCode;
        return this;
    }

    public String getResponseMsg() {
        return responseMsg;
    }

    public ResultBean<T> setResponseMsg(String responseMsg) {
        this.responseMsg = responseMsg;
        return this;
    }

    public T getData() {
        return data;
    }

    public ResultBean<T> setData(T data) {
        this.data = data;
        return this;
    }
}
```



**ResultBean.class**

```txt
cafe babe 0000 0034 0049 0a00 0c00 3c0a
000b 003d 0a00 0b00 3e08 003f 0a00 0b00
400a 000b 0041 0900 0b00 4209 000b 0043
0900 0b00 4409 000b 0045 0700 4607 0047
0700 4801 0009 6973 5375 6363 6573 7301
0001 5a01 000c 7265 7370 6f6e 7365 436f
6465 0100 0149 0100 0b72 6573 706f 6e73
654d 7367 0100 124c 6a61 7661 2f6c 616e
672f 5374 7269 6e67 3b01 0004 6461 7461
0100 124c 6a61 7661 2f6c 616e 672f 4f62
6a65 6374 3b01 0009 5369 676e 6174 7572
6501 0003 5454 3b01 0006 3c69 6e69 743e
0100 0328 2956 0100 0443 6f64 6501 000f
4c69 6e65 4e75 6d62 6572 5461 626c 6501
0012 4c6f 6361 6c56 6172 6961 626c 6554
6162 6c65 0100 0474 6869 7301 002b 4c63
6f6d 2f79 7569 2f74 6f6f 6c2f 6479 6e61
6d69 632f 6475 6262 6f2f 6474 6f2f 5265
7375 6c74 4265 616e 3b01 0016 4c6f 6361
6c56 6172 6961 626c 6554 7970 6554 6162
6c65 0100 304c 636f 6d2f 7975 692f 746f
6f6c 2f64 796e 616d 6963 2f64 7562 626f
2f64 746f 2f52 6573 756c 7442 6561 6e3c
5454 3b3e 3b01 0009 746f 5375 6363 6573
7301 003f 284c 6a61 7661 2f6c 616e 672f
4f62 6a65 6374 3b29 4c63 6f6d 2f79 7569
2f74 6f6f 6c2f 6479 6e61 6d69 632f 6475
6262 6f2f 6474 6f2f 5265 7375 6c74 4265
616e 3b01 0035 2854 543b 294c 636f 6d2f
7975 692f 746f 6f6c 2f64 796e 616d 6963
2f64 7562 626f 2f64 746f 2f52 6573 756c
7442 6561 6e3c 5454 3b3e 3b01 0006 746f
4661 696c 0100 3f28 4c6a 6176 612f 6c61
6e67 2f53 7472 696e 673b 294c 636f 6d2f
7975 692f 746f 6f6c 2f64 796e 616d 6963
2f64 7562 626f 2f64 746f 2f52 6573 756c
7442 6561 6e3b 0100 4428 4c6a 6176 612f
6c61 6e67 2f53 7472 696e 673b 294c 636f
6d2f 7975 692f 746f 6f6c 2f64 796e 616d
6963 2f64 7562 626f 2f64 746f 2f52 6573
756c 7442 6561 6e3c 5454 3b3e 3b01 000c
6765 7449 7353 7563 6365 7373 0100 0328
295a 0100 0c73 6574 4973 5375 6363 6573
7301 002e 285a 294c 636f 6d2f 7975 692f
746f 6f6c 2f64 796e 616d 6963 2f64 7562
626f 2f64 746f 2f52 6573 756c 7442 6561
6e3b 0100 0773 7563 6365 7373 0100 3328
5a29 4c63 6f6d 2f79 7569 2f74 6f6f 6c2f
6479 6e61 6d69 632f 6475 6262 6f2f 6474
6f2f 5265 7375 6c74 4265 616e 3c54 543b
3e3b 0100 0f67 6574 5265 7370 6f6e 7365
436f 6465 0100 0328 2949 0100 0f73 6574
5265 7370 6f6e 7365 436f 6465 0100 2e28
4929 4c63 6f6d 2f79 7569 2f74 6f6f 6c2f
6479 6e61 6d69 632f 6475 6262 6f2f 6474
6f2f 5265 7375 6c74 4265 616e 3b01 0033
2849 294c 636f 6d2f 7975 692f 746f 6f6c
2f64 796e 616d 6963 2f64 7562 626f 2f64
746f 2f52 6573 756c 7442 6561 6e3c 5454
3b3e 3b01 000e 6765 7452 6573 706f 6e73
654d 7367 0100 1428 294c 6a61 7661 2f6c
616e 672f 5374 7269 6e67 3b01 000e 7365
7452 6573 706f 6e73 654d 7367 0100 0767
6574 4461 7461 0100 1428 294c 6a61 7661
2f6c 616e 672f 4f62 6a65 6374 3b01 0005
2829 5454 3b01 0007 7365 7444 6174 6101
003e 3c54 3a4c 6a61 7661 2f6c 616e 672f
4f62 6a65 6374 3b3e 4c6a 6176 612f 6c61
6e67 2f4f 626a 6563 743b 4c6a 6176 612f
696f 2f53 6572 6961 6c69 7a61 626c 653b
0100 0a53 6f75 7263 6546 696c 6501 000f
5265 7375 6c74 4265 616e 2e6a 6176 610c
0018 0019 0c00 3800 220c 002f 0030 0100
0fe6 938d e4bd 9ce6 8890 e58a 9fef bc81
0c00 3400 250c 0029 002a 0c00 0e00 0f0c
0010 0011 0c00 1200 130c 0014 0015 0100
2963 6f6d 2f79 7569 2f74 6f6f 6c2f 6479
6e61 6d69 632f 6475 6262 6f2f 6474 6f2f
5265 7375 6c74 4265 616e 0100 106a 6176
612f 6c61 6e67 2f4f 626a 6563 7401 0014
6a61 7661 2f69 6f2f 5365 7269 616c 697a
6162 6c65 0021 000b 000c 0001 000d 0004
0002 000e 000f 0000 0002 0010 0011 0000
0002 0012 0013 0000 0002 0014 0015 0001
0016 0000 0002 0017 000b 0001 0018 0019
0001 001a 0000 0045 0001 0001 0000 0005
2ab7 0001 b100 0000 0300 1b00 0000 0a00
0200 0000 0f00 0400 1000 1c00 0000 0c00
0100 0000 0500 1d00 1e00 0000 1f00 0000
0c00 0100 0000 0500 1d00 2000 0000 0100
2100 2200 0200 1a00 0000 7b00 0200 0200
0000 1b2a 2bb6 0002 572a 03b6 0003 572a
1204 b600 0557 2a04 b600 0657 2ab0 0000
0003 001b 0000 0016 0005 0000 0013 0006
0014 000c 0015 0013 0016 0019 0017 001c
0000 0016 0002 0000 001b 001d 001e 0000
0000 001b 0014 0015 0001 001f 0000 0016
0002 0000 001b 001d 0020 0000 0000 001b
0014 0017 0001 0016 0000 0002 0023 0001
0024 0025 0002 001a 0000 0054 0002 0002
0000 000e 2a02 b600 032b b600 0503 b600
06b0 0000 0003 001b 0000 0006 0001 0000
001a 001c 0000 0016 0002 0000 000e 001d
001e 0000 0000 000e 0012 0013 0001 001f
0000 000c 0001 0000 000e 001d 0020 0000
0016 0000 0002 0026 0001 0027 0028 0001
001a 0000 0041 0001 0001 0000 0005 2ab4
0007 ac00 0000 0300 1b00 0000 0600 0100
0000 1e00 1c00 0000 0c00 0100 0000 0500
1d00 1e00 0000 1f00 0000 0c00 0100 0000
0500 1d00 2000 0000 0100 2900 2a00 0200
1a00 0000 5100 0200 0200 0000 072a 1bb5
0007 2ab0 0000 0003 001b 0000 000a 0002
0000 0022 0005 0023 001c 0000 0016 0002
0000 0007 001d 001e 0000 0000 0007 002b
000f 0001 001f 0000 000c 0001 0000 0007
001d 0020 0000 0016 0000 0002 002c 0001
002d 002e 0001 001a 0000 0041 0001 0001
0000 0005 2ab4 0008 ac00 0000 0300 1b00
0000 0600 0100 0000 2700 1c00 0000 0c00
0100 0000 0500 1d00 1e00 0000 1f00 0000
0c00 0100 0000 0500 1d00 2000 0000 0100
2f00 3000 0200 1a00 0000 5100 0200 0200
0000 072a 1bb5 0008 2ab0 0000 0003 001b
0000 000a 0002 0000 002b 0005 002c 001c
0000 0016 0002 0000 0007 001d 001e 0000
0000 0007 0010 0011 0001 001f 0000 000c
0001 0000 0007 001d 0020 0000 0016 0000
0002 0031 0001 0032 0033 0001 001a 0000
0041 0001 0001 0000 0005 2ab4 0009 b000
0000 0300 1b00 0000 0600 0100 0000 3000
1c00 0000 0c00 0100 0000 0500 1d00 1e00
0000 1f00 0000 0c00 0100 0000 0500 1d00
2000 0000 0100 3400 2500 0200 1a00 0000
5100 0200 0200 0000 072a 2bb5 0009 2ab0
0000 0003 001b 0000 000a 0002 0000 0034
0005 0035 001c 0000 0016 0002 0000 0007
001d 001e 0000 0000 0007 0012 0013 0001
001f 0000 000c 0001 0000 0007 001d 0020
0000 0016 0000 0002 0026 0001 0035 0036
0002 001a 0000 0041 0001 0001 0000 0005
2ab4 000a b000 0000 0300 1b00 0000 0600
0100 0000 3900 1c00 0000 0c00 0100 0000
0500 1d00 1e00 0000 1f00 0000 0c00 0100
0000 0500 1d00 2000 0000 1600 0000 0200
3700 0100 3800 2200 0200 1a00 0000 5b00
0200 0200 0000 072a 2bb5 000a 2ab0 0000
0003 001b 0000 000a 0002 0000 003d 0005
003e 001c 0000 0016 0002 0000 0007 001d
001e 0000 0000 0007 0014 0015 0001 001f
0000 0016 0002 0000 0007 001d 0020 0000
0000 0007 0014 0017 0001 0016 0000 0002
0023 0002 0016 0000 0002 0039 003a 0000
0002 003b 
```



> javap -v ResultBean.class > ResultBean.classp

**ResultBean.classp**

```java
Classfile /C:/Users/haogg/Desktop/ResultBean.class
  Last modified 2020-4-23; size 2452 bytes
  MD5 checksum dfd60b46fede04570ea444d752c75537
  Compiled from "ResultBean.java"
public class com.yui.tool.dynamic.dubbo.dto.ResultBean<T extends java.lang.Object> extends java.lang.Object implements java.io.Serializable
  minor version: 0
  major version: 52
  flags: ACC_PUBLIC, ACC_SUPER
Constant pool:
   #1 = Methodref          #12.#60        // java/lang/Object."<init>":()V
   #2 = Methodref          #11.#61        // com/yui/tool/dynamic/dubbo/dto/ResultBean.setData:(Ljava/lang/Object;)Lcom/yui/tool/dynamic/dubbo/dto/ResultBean;
   #3 = Methodref          #11.#62        // com/yui/tool/dynamic/dubbo/dto/ResultBean.setResponseCode:(I)Lcom/yui/tool/dynamic/dubbo/dto/ResultBean;
   #4 = String             #63            // 操作成功！
   #5 = Methodref          #11.#64        // com/yui/tool/dynamic/dubbo/dto/ResultBean.setResponseMsg:(Ljava/lang/String;)Lcom/yui/tool/dynamic/dubbo/dto/ResultBean;
   #6 = Methodref          #11.#65        // com/yui/tool/dynamic/dubbo/dto/ResultBean.setIsSuccess:(Z)Lcom/yui/tool/dynamic/dubbo/dto/ResultBean;
   #7 = Fieldref           #11.#66        // com/yui/tool/dynamic/dubbo/dto/ResultBean.isSuccess:Z
   #8 = Fieldref           #11.#67        // com/yui/tool/dynamic/dubbo/dto/ResultBean.responseCode:I
   #9 = Fieldref           #11.#68        // com/yui/tool/dynamic/dubbo/dto/ResultBean.responseMsg:Ljava/lang/String;
  #10 = Fieldref           #11.#69        // com/yui/tool/dynamic/dubbo/dto/ResultBean.data:Ljava/lang/Object;
  #11 = Class              #70            // com/yui/tool/dynamic/dubbo/dto/ResultBean
  #12 = Class              #71            // java/lang/Object
  #13 = Class              #72            // java/io/Serializable
  #14 = Utf8               isSuccess
  #15 = Utf8               Z
  #16 = Utf8               responseCode
  #17 = Utf8               I
  #18 = Utf8               responseMsg
  #19 = Utf8               Ljava/lang/String;
  #20 = Utf8               data
  #21 = Utf8               Ljava/lang/Object;
  #22 = Utf8               Signature
  #23 = Utf8               TT;
  #24 = Utf8               <init>
  #25 = Utf8               ()V
  #26 = Utf8               Code
  #27 = Utf8               LineNumberTable
  #28 = Utf8               LocalVariableTable
  #29 = Utf8               this
  #30 = Utf8               Lcom/yui/tool/dynamic/dubbo/dto/ResultBean;
  #31 = Utf8               LocalVariableTypeTable
  #32 = Utf8               Lcom/yui/tool/dynamic/dubbo/dto/ResultBean<TT;>;
  #33 = Utf8               toSuccess
  #34 = Utf8               (Ljava/lang/Object;)Lcom/yui/tool/dynamic/dubbo/dto/ResultBean;
  #35 = Utf8               (TT;)Lcom/yui/tool/dynamic/dubbo/dto/ResultBean<TT;>;
  #36 = Utf8               toFail
  #37 = Utf8               (Ljava/lang/String;)Lcom/yui/tool/dynamic/dubbo/dto/ResultBean;
  #38 = Utf8               (Ljava/lang/String;)Lcom/yui/tool/dynamic/dubbo/dto/ResultBean<TT;>;
  #39 = Utf8               getIsSuccess
  #40 = Utf8               ()Z
  #41 = Utf8               setIsSuccess
  #42 = Utf8               (Z)Lcom/yui/tool/dynamic/dubbo/dto/ResultBean;
  #43 = Utf8               success
  #44 = Utf8               (Z)Lcom/yui/tool/dynamic/dubbo/dto/ResultBean<TT;>;
  #45 = Utf8               getResponseCode
  #46 = Utf8               ()I
  #47 = Utf8               setResponseCode
  #48 = Utf8               (I)Lcom/yui/tool/dynamic/dubbo/dto/ResultBean;
  #49 = Utf8               (I)Lcom/yui/tool/dynamic/dubbo/dto/ResultBean<TT;>;
  #50 = Utf8               getResponseMsg
  #51 = Utf8               ()Ljava/lang/String;
  #52 = Utf8               setResponseMsg
  #53 = Utf8               getData
  #54 = Utf8               ()Ljava/lang/Object;
  #55 = Utf8               ()TT;
  #56 = Utf8               setData
  #57 = Utf8               <T:Ljava/lang/Object;>Ljava/lang/Object;Ljava/io/Serializable;
  #58 = Utf8               SourceFile
  #59 = Utf8               ResultBean.java
  #60 = NameAndType        #24:#25        // "<init>":()V
  #61 = NameAndType        #56:#34        // setData:(Ljava/lang/Object;)Lcom/yui/tool/dynamic/dubbo/dto/ResultBean;
  #62 = NameAndType        #47:#48        // setResponseCode:(I)Lcom/yui/tool/dynamic/dubbo/dto/ResultBean;
  #63 = Utf8               操作成功！
  #64 = NameAndType        #52:#37        // setResponseMsg:(Ljava/lang/String;)Lcom/yui/tool/dynamic/dubbo/dto/ResultBean;
  #65 = NameAndType        #41:#42        // setIsSuccess:(Z)Lcom/yui/tool/dynamic/dubbo/dto/ResultBean;
  #66 = NameAndType        #14:#15        // isSuccess:Z
  #67 = NameAndType        #16:#17        // responseCode:I
  #68 = NameAndType        #18:#19        // responseMsg:Ljava/lang/String;
  #69 = NameAndType        #20:#21        // data:Ljava/lang/Object;
  #70 = Utf8               com/yui/tool/dynamic/dubbo/dto/ResultBean
  #71 = Utf8               java/lang/Object
  #72 = Utf8               java/io/Serializable
{
  public com.yui.tool.dynamic.dubbo.dto.ResultBean();
    descriptor: ()V
    flags: ACC_PUBLIC
    Code:
      stack=1, locals=1, args_size=1
         0: aload_0
         1: invokespecial #1                  // Method java/lang/Object."<init>":()V
         4: return
      LineNumberTable:
        line 15: 0
        line 16: 4
      LocalVariableTable:
        Start  Length  Slot  Name   Signature
            0       5     0  this   Lcom/yui/tool/dynamic/dubbo/dto/ResultBean;
      LocalVariableTypeTable:
        Start  Length  Slot  Name   Signature
            0       5     0  this   Lcom/yui/tool/dynamic/dubbo/dto/ResultBean<TT;>;

  public com.yui.tool.dynamic.dubbo.dto.ResultBean<T> toSuccess(T);
    descriptor: (Ljava/lang/Object;)Lcom/yui/tool/dynamic/dubbo/dto/ResultBean;
    flags: ACC_PUBLIC
    Code:
      stack=2, locals=2, args_size=2
         0: aload_0
         1: aload_1
         2: invokevirtual #2                  // Method setData:(Ljava/lang/Object;)Lcom/yui/tool/dynamic/dubbo/dto/ResultBean;
         5: pop
         6: aload_0
         7: iconst_0
         8: invokevirtual #3                  // Method setResponseCode:(I)Lcom/yui/tool/dynamic/dubbo/dto/ResultBean;
        11: pop
        12: aload_0
        13: ldc           #4                  // String 操作成功！
        15: invokevirtual #5                  // Method setResponseMsg:(Ljava/lang/String;)Lcom/yui/tool/dynamic/dubbo/dto/ResultBean;
        18: pop
        19: aload_0
        20: iconst_1
        21: invokevirtual #6                  // Method setIsSuccess:(Z)Lcom/yui/tool/dynamic/dubbo/dto/ResultBean;
        24: pop
        25: aload_0
        26: areturn
      LineNumberTable:
        line 19: 0
        line 20: 6
        line 21: 12
        line 22: 19
        line 23: 25
      LocalVariableTable:
        Start  Length  Slot  Name   Signature
            0      27     0  this   Lcom/yui/tool/dynamic/dubbo/dto/ResultBean;
            0      27     1  data   Ljava/lang/Object;
      LocalVariableTypeTable:
        Start  Length  Slot  Name   Signature
            0      27     0  this   Lcom/yui/tool/dynamic/dubbo/dto/ResultBean<TT;>;
            0      27     1  data   TT;
    Signature: #35                          // (TT;)Lcom/yui/tool/dynamic/dubbo/dto/ResultBean<TT;>;

  public com.yui.tool.dynamic.dubbo.dto.ResultBean<T> toFail(java.lang.String);
    descriptor: (Ljava/lang/String;)Lcom/yui/tool/dynamic/dubbo/dto/ResultBean;
    flags: ACC_PUBLIC
    Code:
      stack=2, locals=2, args_size=2
         0: aload_0
         1: iconst_m1
         2: invokevirtual #3                  // Method setResponseCode:(I)Lcom/yui/tool/dynamic/dubbo/dto/ResultBean;
         5: aload_1
         6: invokevirtual #5                  // Method setResponseMsg:(Ljava/lang/String;)Lcom/yui/tool/dynamic/dubbo/dto/ResultBean;
         9: iconst_0
        10: invokevirtual #6                  // Method setIsSuccess:(Z)Lcom/yui/tool/dynamic/dubbo/dto/ResultBean;
        13: areturn
      LineNumberTable:
        line 26: 0
      LocalVariableTable:
        Start  Length  Slot  Name   Signature
            0      14     0  this   Lcom/yui/tool/dynamic/dubbo/dto/ResultBean;
            0      14     1 responseMsg   Ljava/lang/String;
      LocalVariableTypeTable:
        Start  Length  Slot  Name   Signature
            0      14     0  this   Lcom/yui/tool/dynamic/dubbo/dto/ResultBean<TT;>;
    Signature: #38                          // (Ljava/lang/String;)Lcom/yui/tool/dynamic/dubbo/dto/ResultBean<TT;>;

  public boolean getIsSuccess();
    descriptor: ()Z
    flags: ACC_PUBLIC
    Code:
      stack=1, locals=1, args_size=1
         0: aload_0
         1: getfield      #7                  // Field isSuccess:Z
         4: ireturn
      LineNumberTable:
        line 30: 0
      LocalVariableTable:
        Start  Length  Slot  Name   Signature
            0       5     0  this   Lcom/yui/tool/dynamic/dubbo/dto/ResultBean;
      LocalVariableTypeTable:
        Start  Length  Slot  Name   Signature
            0       5     0  this   Lcom/yui/tool/dynamic/dubbo/dto/ResultBean<TT;>;

  public com.yui.tool.dynamic.dubbo.dto.ResultBean<T> setIsSuccess(boolean);
    descriptor: (Z)Lcom/yui/tool/dynamic/dubbo/dto/ResultBean;
    flags: ACC_PUBLIC
    Code:
      stack=2, locals=2, args_size=2
         0: aload_0
         1: iload_1
         2: putfield      #7                  // Field isSuccess:Z
         5: aload_0
         6: areturn
      LineNumberTable:
        line 34: 0
        line 35: 5
      LocalVariableTable:
        Start  Length  Slot  Name   Signature
            0       7     0  this   Lcom/yui/tool/dynamic/dubbo/dto/ResultBean;
            0       7     1 success   Z
      LocalVariableTypeTable:
        Start  Length  Slot  Name   Signature
            0       7     0  this   Lcom/yui/tool/dynamic/dubbo/dto/ResultBean<TT;>;
    Signature: #44                          // (Z)Lcom/yui/tool/dynamic/dubbo/dto/ResultBean<TT;>;

  public int getResponseCode();
    descriptor: ()I
    flags: ACC_PUBLIC
    Code:
      stack=1, locals=1, args_size=1
         0: aload_0
         1: getfield      #8                  // Field responseCode:I
         4: ireturn
      LineNumberTable:
        line 39: 0
      LocalVariableTable:
        Start  Length  Slot  Name   Signature
            0       5     0  this   Lcom/yui/tool/dynamic/dubbo/dto/ResultBean;
      LocalVariableTypeTable:
        Start  Length  Slot  Name   Signature
            0       5     0  this   Lcom/yui/tool/dynamic/dubbo/dto/ResultBean<TT;>;

  public com.yui.tool.dynamic.dubbo.dto.ResultBean<T> setResponseCode(int);
    descriptor: (I)Lcom/yui/tool/dynamic/dubbo/dto/ResultBean;
    flags: ACC_PUBLIC
    Code:
      stack=2, locals=2, args_size=2
         0: aload_0
         1: iload_1
         2: putfield      #8                  // Field responseCode:I
         5: aload_0
         6: areturn
      LineNumberTable:
        line 43: 0
        line 44: 5
      LocalVariableTable:
        Start  Length  Slot  Name   Signature
            0       7     0  this   Lcom/yui/tool/dynamic/dubbo/dto/ResultBean;
            0       7     1 responseCode   I
      LocalVariableTypeTable:
        Start  Length  Slot  Name   Signature
            0       7     0  this   Lcom/yui/tool/dynamic/dubbo/dto/ResultBean<TT;>;
    Signature: #49                          // (I)Lcom/yui/tool/dynamic/dubbo/dto/ResultBean<TT;>;

  public java.lang.String getResponseMsg();
    descriptor: ()Ljava/lang/String;
    flags: ACC_PUBLIC
    Code:
      stack=1, locals=1, args_size=1
         0: aload_0
         1: getfield      #9                  // Field responseMsg:Ljava/lang/String;
         4: areturn
      LineNumberTable:
        line 48: 0
      LocalVariableTable:
        Start  Length  Slot  Name   Signature
            0       5     0  this   Lcom/yui/tool/dynamic/dubbo/dto/ResultBean;
      LocalVariableTypeTable:
        Start  Length  Slot  Name   Signature
            0       5     0  this   Lcom/yui/tool/dynamic/dubbo/dto/ResultBean<TT;>;

  public com.yui.tool.dynamic.dubbo.dto.ResultBean<T> setResponseMsg(java.lang.String);
    descriptor: (Ljava/lang/String;)Lcom/yui/tool/dynamic/dubbo/dto/ResultBean;
    flags: ACC_PUBLIC
    Code:
      stack=2, locals=2, args_size=2
         0: aload_0
         1: aload_1
         2: putfield      #9                  // Field responseMsg:Ljava/lang/String;
         5: aload_0
         6: areturn
      LineNumberTable:
        line 52: 0
        line 53: 5
      LocalVariableTable:
        Start  Length  Slot  Name   Signature
            0       7     0  this   Lcom/yui/tool/dynamic/dubbo/dto/ResultBean;
            0       7     1 responseMsg   Ljava/lang/String;
      LocalVariableTypeTable:
        Start  Length  Slot  Name   Signature
            0       7     0  this   Lcom/yui/tool/dynamic/dubbo/dto/ResultBean<TT;>;
    Signature: #38                          // (Ljava/lang/String;)Lcom/yui/tool/dynamic/dubbo/dto/ResultBean<TT;>;

  public T getData();
    descriptor: ()Ljava/lang/Object;
    flags: ACC_PUBLIC
    Code:
      stack=1, locals=1, args_size=1
         0: aload_0
         1: getfield      #10                 // Field data:Ljava/lang/Object;
         4: areturn
      LineNumberTable:
        line 57: 0
      LocalVariableTable:
        Start  Length  Slot  Name   Signature
            0       5     0  this   Lcom/yui/tool/dynamic/dubbo/dto/ResultBean;
      LocalVariableTypeTable:
        Start  Length  Slot  Name   Signature
            0       5     0  this   Lcom/yui/tool/dynamic/dubbo/dto/ResultBean<TT;>;
    Signature: #55                          // ()TT;

  public com.yui.tool.dynamic.dubbo.dto.ResultBean<T> setData(T);
    descriptor: (Ljava/lang/Object;)Lcom/yui/tool/dynamic/dubbo/dto/ResultBean;
    flags: ACC_PUBLIC
    Code:
      stack=2, locals=2, args_size=2
         0: aload_0
         1: aload_1
         2: putfield      #10                 // Field data:Ljava/lang/Object;
         5: aload_0
         6: areturn
      LineNumberTable:
        line 61: 0
        line 62: 5
      LocalVariableTable:
        Start  Length  Slot  Name   Signature
            0       7     0  this   Lcom/yui/tool/dynamic/dubbo/dto/ResultBean;
            0       7     1  data   Ljava/lang/Object;
      LocalVariableTypeTable:
        Start  Length  Slot  Name   Signature
            0       7     0  this   Lcom/yui/tool/dynamic/dubbo/dto/ResultBean<TT;>;
            0       7     1  data   TT;
    Signature: #35                          // (TT;)Lcom/yui/tool/dynamic/dubbo/dto/ResultBean<TT;>;
}
Signature: #57                          // <T:Ljava/lang/Object;>Ljava/lang/Object;Ljava/io/Serializable;
SourceFile: "ResultBean.java"
```





### 1.3 字节码指令

